evonik/__init__.py
evonik/openapi/__init__.py
evonik/openapi/openapi.py
evonik_openapi-0.0.7.data/scripts/evonik-openapi
evonik_openapi-0.0.7.dist-info/LICENSE
evonik_openapi-0.0.7.dist-info/METADATA
evonik_openapi-0.0.7.dist-info/WHEEL
evonik_openapi-0.0.7.dist-info/top_level.txt
evonik_openapi-0.0.7.dist-info/RECORD
