Metadata-Version: 2.1
Name: evonik-openapi
Version: 0.0.7
Summary: Generate and merge client/server stubs using openapi-generator
Home-page: https://evodl.visualstudio.com/openapi
Author: Benjamin Schiller
Author-email: benjamin.schiller@evonik.com
License: UNKNOWN
Platform: UNKNOWN
Classifier: Programming Language :: Python :: 3
Classifier: License :: OSI Approved :: MIT License
Classifier: Operating System :: OS Independent
Requires-Python: >=3.6
Requires-Dist: uuid
